lazydata/__init__.py
lazydata/tracker.py
lazydata/bin/__init__.py
lazydata/cli/__init__.py
lazydata/cli/cli.py
lazydata/cli/commands/BaseCommand.py
lazydata/cli/commands/__init__.py
lazydata/cli/commands/addremote.py
lazydata/cli/commands/config.py
lazydata/cli/commands/configremote.py
lazydata/cli/commands/init.py
lazydata/cli/commands/ls.py
lazydata/cli/commands/pull.py
lazydata/cli/commands/push.py
lazydata/cli/commands/removeremote.py
lazydata/cli/commands/status.py
lazydata/config/__init__.py
lazydata/config/config.py
lazydata/storage/__init__.py
lazydata/storage/cloudsetup.py
lazydata/storage/fetch_file.py
lazydata/storage/hash.py
lazydata/storage/local.py
lazydata/storage/remote.py
lazydata-1.0.19.data/scripts/lazydata
lazydata-1.0.19.dist-info/METADATA
lazydata-1.0.19.dist-info/RECORD
lazydata-1.0.19.dist-info/WHEEL
lazydata-1.0.19.dist-info/entry_points.txt
lazydata-1.0.19.dist-info/top_level.txt
