Metadata-Version: 2.1
Name: lazydata
Version: 1.0.19
Summary: Scalable data dependencies
Home-page: https://github.com/rstojnic/lazydata
Author: Robert Stojnic
Author-email: robert.stojnic@gmail.com
License: UNKNOWN
Platform: UNKNOWN
Classifier: Programming Language :: Python :: 3
Classifier: License :: OSI Approved :: Apache Software License
Classifier: Operating System :: OS Independent
Requires-Python: >=3.5.2
Requires-Dist: pyyaml
Requires-Dist: peewee
Requires-Dist: boto3
Requires-Dist: lazy-import
